streamlit_image_select_mod/__init__.py
streamlit_image_select_mod/frontend/.env
streamlit_image_select_mod/frontend/.prettierrc
streamlit_image_select_mod/frontend/build/asset-manifest.json
streamlit_image_select_mod/frontend/build/index.html
streamlit_image_select_mod/frontend/build/precache-manifest.8603a2be0d18267ec080c65571a01b12.js
streamlit_image_select_mod/frontend/build/service-worker.js
streamlit_image_select_mod/frontend/build/static/js/2.958830ed.chunk.js
streamlit_image_select_mod/frontend/build/static/js/2.958830ed.chunk.js.LICENSE.txt
streamlit_image_select_mod/frontend/build/static/js/2.958830ed.chunk.js.map
streamlit_image_select_mod/frontend/build/static/js/main.3ccdfe00.chunk.js
streamlit_image_select_mod/frontend/build/static/js/main.3ccdfe00.chunk.js.map
streamlit_image_select_mod/frontend/build/static/js/runtime-main.fce4c018.js
streamlit_image_select_mod/frontend/build/static/js/runtime-main.fce4c018.js.map
streamlit_image_select_mod/frontend/build/styles.css
streamlit_image_select_mod/frontend/package-lock.json
streamlit_image_select_mod/frontend/package.json
streamlit_image_select_mod/frontend/public/index.html
streamlit_image_select_mod/frontend/public/styles.css
streamlit_image_select_mod/frontend/src/index.tsx
streamlit_image_select_mod/frontend/src/react-app-env.d.ts
streamlit_image_select_mod/frontend/tsconfig.json
streamlit_image_select_mod/~/.pypirc
streamlit_image_select_mod-0.1.2.dist-info/LICENSE
streamlit_image_select_mod-0.1.2.dist-info/WHEEL
streamlit_image_select_mod-0.1.2.dist-info/METADATA
streamlit_image_select_mod-0.1.2.dist-info/RECORD
